SteveSmithThing2/__init__.py
SteveSmithThing2/factorial.py
SteveSmithThing2/fibonacci.py
SteveSmithThing2-0.0.4.dist-info/LICENSE.txt
SteveSmithThing2-0.0.4.dist-info/METADATA
SteveSmithThing2-0.0.4.dist-info/WHEEL
SteveSmithThing2-0.0.4.dist-info/top_level.txt
SteveSmithThing2-0.0.4.dist-info/RECORD
