Metadata-Version: 2.1
Name: SteveSmithThing2
Version: 0.0.4
Summary: It tells the factorial of a number
Home-page: https://github.com/STEVE-al/Factorial
Author: steve
Author-email: s.smith200712@gmail.com
License: UNKNOWN
Platform: UNKNOWN
Classifier: Programming Language :: Python :: 3
Classifier: License :: OSI Approved :: MIT License
Classifier: Operating System :: OS Independent
Requires-Python: >=3.6
